[
  {
    "languages": [
      "English",
      "Arabic",
      "Azerbaijani",
      "Bulgarian",
      "Croatian",
      "Czech",
      "Danish",
      "Dutch",
      "Estonian",
      "Finnish",
      "French",
      "German",
      "Greek",
      "Hebrew",
      "Hindi",
      "Hungarian",
      "Indonesian",
      "Italian",
      "Japanese",
      "Korean",
      "Latvian",
      "Lithuanian",
      "Malay",
      "Norwegian Bokm\u00e5l",
      "Polish",
      "Portuguese",
      "Romanian",
      "Russian",
      "Simplified Chinese",
      "Slovak",
      "Slovenian",
      "Spanish",
      "Swahili",
      "Swedish",
      "Tagalog",
      "Thai",
      "Traditional Chinese",
      "Turkish",
      "Ukrainian",
      "Urdu",
      "Vietnamese"
    ],
    "app_identifier": "68677368",
    "name": "Uber",
    "minimum_version": "9.0"
  },
  {
    "languages": [
      "English"
    ],
    "app_identifier": "261357853",
    "name": "Fortnite",
    "minimum_version": "11.0"
  },
  {
    "languages": [
      "English",
      "Afrikaans",
      "Arabic",
      "Bengali",
      "Bulgarian",
      "Catalan",
      "Croatian",
      "Czech",
      "Danish",
      "Dutch",
      "Filipino",
      "Finnish",
      "French",
      "German",
      "Greek",
      "Hebrew",
      "Hindi",
      "Hungarian",
      "Indonesian",
      "Italian",
      "Japanese",
      "Korean",
      "Latvian",
      "Lithuanian",
      "Malay",
      "Norwegian Bokm\u00e5l",
      "Polish",
      "Portuguese",
      "Romanian",
      "Russian",
      "Serbian",
      "Simplified Chinese",
      "Slovak",
      "Slovenian",
      "Spanish",
      "Swedish",
      "Tamil",
      "Telugu",
      "Thai",
      "Traditional Chinese",
      "Turkish",
      "Ukrainian",
      "Vietnamese"
    ],
    "app_identifier": "47702041",
    "name": "Tinder",
    "minimum_version": "9.0"
  },
  {
    "languages": [
      "English",
      "Croatian",
      "Czech",
      "Danish",
      "Dutch",
      "Finnish",
      "French",
      "German",
      "Greek",
      "Indonesian",
      "Italian",
      "Japanese",
      "Korean",
      "Malay",
      "Norwegian Bokm\u00e5l",
      "Polish",
      "Portuguese",
      "Romanian",
      "Russian",
      "Simplified Chinese",
      "Slovak",
      "Spanish",
      "Swedish",
      "Tagalog",
      "Thai",
      "Traditional Chinese",
      "Turkish",
      "Ukrainian",
      "Vietnamese"
    ],
    "app_identifier": "89801252",
    "name": "Instagram",
    "minimum_version": "9.0"
  }
]